lmdeployv1/__init__.py
lmdeployv1/api.py
lmdeployv1/client.py
lmdeployv1/example.py
lmdeployv1-0.0.9.4.dist-info/METADATA
lmdeployv1-0.0.9.4.dist-info/WHEEL
lmdeployv1-0.0.9.4.dist-info/top_level.txt
lmdeployv1-0.0.9.4.dist-info/RECORD
