Metadata-Version: 2.1
Name: lmdeployv1
Version: 0.0.9.4
Summary: LMDeploy api client
Requires-Python: >=3.8
Requires-Dist: bceidaas ==0.0.1.dev2
Requires-Dist: openai ==1.55.3
Requires-Dist: pyrate-limiter ~=2.10.0
Requires-Dist: tenacity ==8.2.2
